
{"result_count":20,"total_count":"640","next_offset":20,"entry_list":[{"id":"ae2ebb83-a4b3-c377-e068-50047613b963","name":"John Tester","date_entered":"2012-07-16 20:14:33","date_modified":"2012-07-16 20:14:33","description":"","first_name":"John","last_name":"Tester","full_name":"John Tester","email":"","email1":"","email2":"","avatar_id":"","facebook_id":"","sip_status":"offline"},{"id":"3e72220b-7f73-f966-3ca9-500476890086","name":"James Tester","date_entered":"2012-07-16 20:15:14","date_modified":"2012-07-17 13:42:22","description":"","first_name":"James","last_name":"Tester","full_name":"James Tester","email":"","email1":"","email2":"","avatar_id":"","facebook_id":"","sip_status":"offline"},{"id":"327fab10-1c5c-6bc3-dfa6-50056b39fed7","name":"Tester Junior","date_entered":"2012-07-17 13:41:53","date_modified":"2012-07-17 13:41:53","description":"","first_name":"Tester","last_name":"Junior","full_name":"Tester Junior","email":"","email1":"","email2":"","avatar_id":"","facebook_id":"","sip_status":"offline"},{"id":"4ebac383-0a3b-a5e6-5583-4fff5de07836","name":"tester","date_entered":"2012-07-12 23:29:47","date_modified":"2012-07-12 23:29:47","description":"","first_name":"","last_name":"tester","full_name":"tester","email":"","email1":"","email2":"","avatar_id":"","facebook_id":"","sip_status":"offline"},{"id":"bc2103c0-6d7a-6ef5-7ebe-4fff63059ee0","name":"Walter Hoover","date_entered":"2012-07-12 23:55:38","date_modified":"2012-07-12 23:55:38","description":"","first_name":"Walter","last_name":"Hoover","full_name":"Walter Hoover","email":"","email1":"","email2":"","avatar_id":"a216e3c8-4329-8a84-1f74-4ff72bef20c9","facebook_id":"","sip_status":"offline","avatar_url":"http:\/\/api.cods.pyctex.net\/images\/a216e3c8-4329-8a84-1f74-4ff72bef20c9"},{"id":"bd52d4c1-d06e-c591-ef5b-4fff6309e080","name":"Dan Glenn","date_entered":"2012-07-12 23:55:38","date_modified":"2012-07-12 23:55:38","description":"","first_name":"Dan","last_name":"Glenn","full_name":"Dan Glenn","email":"","email1":"","email2":"","avatar_id":"7a842848-c318-b0fc-8ca9-4ff74b1395cf","facebook_id":"","sip_status":"offline","avatar_url":"http:\/\/api.cods.pyctex.net\/images\/7a842848-c318-b0fc-8ca9-4ff74b1395cf"},{"id":"bdfa0058-00e9-f4f5-c9b5-4fff63410534","name":"Steven King","date_entered":"2012-07-12 23:55:38","date_modified":"2012-07-12 23:55:38","description":"","first_name":"Steven","last_name":"King","full_name":"Steven King","email":"","email1":"","email2":"","avatar_id":"b9657907-38df-e171-cd1c-4ff741ef4fb0","facebook_id":"","sip_status":"offline","avatar_url":"http:\/\/api.cods.pyctex.net\/images\/b9657907-38df-e171-cd1c-4ff741ef4fb0"},{"id":"be9b4585-938b-cc0d-51a2-4fff63c24e08","name":"Norman West","date_entered":"2012-07-12 23:55:38","date_modified":"2012-07-12 23:55:38","description":"","first_name":"Norman","last_name":"West","full_name":"Norman West","email":"","email1":"","email2":"","avatar_id":"84bd3a2e-39b5-9753-d50d-4ff74b575d42","facebook_id":"","sip_status":"offline","avatar_url":"http:\/\/api.cods.pyctex.net\/images\/84bd3a2e-39b5-9753-d50d-4ff74b575d42"},{"id":"bf3c1a83-64b8-3f9b-d3db-4fff63bca589","name":"Mathew Castaneda","date_entered":"2012-07-12 23:55:38","date_modified":"2012-07-12 23:55:38","description":"","first_name":"Mathew","last_name":"Castaneda","full_name":"Mathew Castaneda","email":"","email1":"","email2":"","avatar_id":"7a842848-c318-b0fc-8ca9-4ff74b1395cf","facebook_id":"","sip_status":"offline","avatar_url":"http:\/\/api.cods.pyctex.net\/images\/7a842848-c318-b0fc-8ca9-4ff74b1395cf"},{"id":"bfdf2ed6-751c-0c1c-a13a-4fff638fe847","name":"Jerry Houston","date_entered":"2012-07-12 23:55:38","date_modified":"2012-07-12 23:55:38","description":"","first_name":"Jerry","last_name":"Houston","full_name":"Jerry Houston","email":"","email1":"","email2":"","avatar_id":"f171e97a-05d9-d464-80b8-4ff741476e0a","facebook_id":"","sip_status":"offline","avatar_url":"http:\/\/api.cods.pyctex.net\/images\/f171e97a-05d9-d464-80b8-4ff741476e0a"},{"id":"c07eab69-2614-e017-c3d6-4fff6352e37e","name":"Marion Holloway","date_entered":"2012-07-12 23:55:38","date_modified":"2012-07-12 23:55:38","description":"","first_name":"Marion","last_name":"Holloway","full_name":"Marion Holloway","email":"","email1":"","email2":"","avatar_id":"84bd3a2e-39b5-9753-d50d-4ff74b575d42","facebook_id":"","sip_status":"offline","avatar_url":"http:\/\/api.cods.pyctex.net\/images\/84bd3a2e-39b5-9753-d50d-4ff74b575d42"},{"id":"c11f32a1-9868-6f77-c218-4fff63b196c2","name":"Christian Oconnor","date_entered":"2012-07-12 23:55:38","date_modified":"2012-07-12 23:55:38","description":"","first_name":"Christian","last_name":"Oconnor","full_name":"Christian Oconnor","email":"","email1":"","email2":"","avatar_id":"4a32f0fd-cc43-ab10-d0be-4ff72b79abbf","facebook_id":"","sip_status":"offline","avatar_url":"http:\/\/api.cods.pyctex.net\/images\/4a32f0fd-cc43-ab10-d0be-4ff72b79abbf"},{"id":"c1beaeec-374c-72f0-e721-4fff634751f0","name":"Clinton Contreras","date_entered":"2012-07-12 23:55:38","date_modified":"2012-07-12 23:55:38","description":"","first_name":"Clinton","last_name":"Contreras","full_name":"Clinton Contreras","email":"","email1":"","email2":"","avatar_id":"7a842848-c318-b0fc-8ca9-4ff74b1395cf","facebook_id":"","sip_status":"offline","avatar_url":"http:\/\/api.cods.pyctex.net\/images\/7a842848-c318-b0fc-8ca9-4ff74b1395cf"},{"id":"c25ec5b3-02b9-d85c-7d0c-4fff63abe3f3","name":"Byron Barron","date_entered":"2012-07-12 23:55:38","date_modified":"2012-07-12 23:55:38","description":"","first_name":"Byron","last_name":"Barron","full_name":"Byron Barron","email":"","email1":"","email2":"","avatar_id":"a216e3c8-4329-8a84-1f74-4ff72bef20c9","facebook_id":"","sip_status":"offline","avatar_url":"http:\/\/api.cods.pyctex.net\/images\/a216e3c8-4329-8a84-1f74-4ff72bef20c9"},{"id":"c3004a78-2d11-cb8b-d204-4fff63b8109f","name":"Victor Cherry","date_entered":"2012-07-12 23:55:38","date_modified":"2012-07-12 23:55:38","description":"","first_name":"Victor","last_name":"Cherry","full_name":"Victor Cherry","email":"","email1":"","email2":"","avatar_id":"c81011e0-cfb5-31a2-7021-4ff74c0010ec","facebook_id":"","sip_status":"offline","avatar_url":"http:\/\/api.cods.pyctex.net\/images\/c81011e0-cfb5-31a2-7021-4ff74c0010ec"},{"id":"c3a0d65f-5a77-474a-fd24-4fff63858c15","name":"George Wiley","date_entered":"2012-07-12 23:55:38","date_modified":"2012-07-12 23:55:38","description":"","first_name":"George","last_name":"Wiley","full_name":"George Wiley","email":"","email1":"","email2":"","avatar_id":"a216e3c8-4329-8a84-1f74-4ff72bef20c9","facebook_id":"","sip_status":"offline","avatar_url":"http:\/\/api.cods.pyctex.net\/images\/a216e3c8-4329-8a84-1f74-4ff72bef20c9"},{"id":"c44243a0-4cdb-286f-fad7-4fff630843f8","name":"Kevin Bruce","date_entered":"2012-07-12 23:55:38","date_modified":"2012-07-12 23:55:38","description":"","first_name":"Kevin","last_name":"Bruce","full_name":"Kevin Bruce","email":"","email1":"","email2":"","avatar_id":"a2e0b81f-918a-975c-e870-4ff72b6027ca","facebook_id":"","sip_status":"offline","avatar_url":"http:\/\/api.cods.pyctex.net\/images\/a2e0b81f-918a-975c-e870-4ff72b6027ca"},{"id":"c4e1878d-78b5-59b2-6a6f-4fff63c19bba","name":"Clinton Avila","date_entered":"2012-07-12 23:55:38","date_modified":"2012-07-12 23:55:38","description":"","first_name":"Clinton","last_name":"Avila","full_name":"Clinton Avila","email":"","email1":"","email2":"","avatar_id":"4a32f0fd-cc43-ab10-d0be-4ff72b79abbf","facebook_id":"","sip_status":"offline","avatar_url":"http:\/\/api.cods.pyctex.net\/images\/4a32f0fd-cc43-ab10-d0be-4ff72b79abbf"},{"id":"c5834304-10c4-a411-87f6-4fff635608bb","name":"Antonio Kidd","date_entered":"2012-07-12 23:55:38","date_modified":"2012-07-12 23:55:38","description":"","first_name":"Antonio","last_name":"Kidd","full_name":"Antonio Kidd","email":"","email1":"","email2":"","avatar_id":"4a32f0fd-cc43-ab10-d0be-4ff72b79abbf","facebook_id":"","sip_status":"offline","avatar_url":"http:\/\/api.cods.pyctex.net\/images\/4a32f0fd-cc43-ab10-d0be-4ff72b79abbf"},{"id":"c622ea6c-131d-802d-aee8-4fff63e677ff","name":"Jared Nelson","date_entered":"2012-07-12 23:55:38","date_modified":"2012-07-12 23:55:38","description":"","first_name":"Jared","last_name":"Nelson","full_name":"Jared Nelson","email":"","email1":"","email2":"","avatar_id":"b9657907-38df-e171-cd1c-4ff741ef4fb0","facebook_id":"","sip_status":"offline","avatar_url":"http:\/\/api.cods.pyctex.net\/images\/b9657907-38df-e171-cd1c-4ff741ef4fb0"}],"relationship_list":[]}